{
  "European Schools": [
    {"id": 1, "query": "List all schools", "complexity": 0, "length": 0, "tables": 1, "attributes": 3},
    {"id": 2, "query": "Show school names and countries", "complexity": 0, "length": 1, "tables": 1, "attributes": 2},
    {"id": 3, "query": "Find schools in Germany", "complexity": 0, "length": 1, "tables": 1, "attributes": 3},
    {"id": 4, "query": "What is the average number of students per school by country?", "complexity": 1, "length": 2, "tables": 2, "attributes": 4},
    {"id": 5, "query": "List all students enrolled in 2023", "complexity": 0, "length": 1, "tables": 1, "attributes": 4},
    {"id": 6, "query": "Find the top 5 largest schools by student count", "complexity": 1, "length": 1, "tables": 2, "attributes": 4},
    {"id": 7, "query": "Show schools with their city and student enrollment numbers", "complexity": 1, "length": 2, "tables": 2, "attributes": 5},
    {"id": 8, "query": "Count students by grade level", "complexity": 1, "length": 1, "tables": 1, "attributes": 2},
    {"id": 9, "query": "List schools with more than 500 students", "complexity": 1, "length": 1, "tables": 2, "attributes": 3},
    {"id": 10, "query": "Find students with a GPA above 3.5", "complexity": 1, "length": 1, "tables": 1, "attributes": 3},
    {"id": 11, "query": "Show students with their school names and countries", "complexity": 1, "length": 1, "tables": 2, "attributes": 5},
    {"id": 12, "query": "What is the average GPA by school and grade level?", "complexity": 2, "length": 2, "tables": 2, "attributes": 5},
    {"id": 13, "query": "Find schools that offer both science and arts programs with their accreditation status", "complexity": 2, "length": 2, "tables": 3, "attributes": 7},
    {"id": 14, "query": "List students who participate in at least 2 extracurricular activities", "complexity": 2, "length": 2, "tables": 3, "attributes": 6},
    {"id": 15, "query": "Show countries where the average school size is above the European average", "complexity": 3, "length": 2, "tables": 2, "attributes": 5},
    {"id": 16, "query": "Find students who scored in the top 10% in their school and country", "complexity": 3, "length": 2, "tables": 3, "attributes": 7},
    {"id": 17, "query": "Calculate the student-teacher ratio for each school and rank them", "complexity": 2, "length": 2, "tables": 3, "attributes": 6},
    {"id": 18, "query": "Show the progression of enrollment numbers for each school over the past 5 years", "complexity": 3, "length": 2, "tables": 3, "attributes": 8},
    {"id": 19, "query": "Identify schools with declining enrollment but improving academic performance metrics including standardized test scores", "complexity": 3, "length": 3, "tables": 4, "attributes": 10},
    {"id": 20, "query": "Compare graduation rates and university acceptance rates across different school types and funding models in each country", "complexity": 3, "length": 3, "tables": 5, "attributes": 12},
    {"id": 21, "query": "Which school has the most teachers?", "complexity": 1, "length": 1, "tables": 2, "attributes": 3},
    {"id": 22, "query": "Show all students in grade 12", "complexity": 0, "length": 1, "tables": 1, "attributes": 3},
    {"id": 23, "query": "Find schools established before 1950", "complexity": 0, "length": 1, "tables": 1, "attributes": 3},
    {"id": 24, "query": "What is the total number of students across all schools?", "complexity": 1, "length": 1, "tables": 1, "attributes": 1},
    {"id": 25, "query": "List schools offering bilingual programs", "complexity": 1, "length": 1, "tables": 2, "attributes": 4},
    {"id": 26, "query": "Show the distribution of students by nationality", "complexity": 2, "length": 1, "tables": 2, "attributes": 4},
    {"id": 27, "query": "Find teachers who teach multiple subjects", "complexity": 2, "length": 1, "tables": 3, "attributes": 5},
    {"id": 28, "query": "Which schools have exchange programs with universities and what are the acceptance rates?", "complexity": 3, "length": 2, "tables": 4, "attributes": 8},
    {"id": 29, "query": "Analyze the correlation between school funding and student performance across different regions", "complexity": 3, "length": 3, "tables": 5, "attributes": 10},
    {"id": 30, "query": "Identify patterns in student achievement based on class size, teacher qualifications, and facility quality across all European countries", "complexity": 3, "length": 3, "tables": 6, "attributes": 12}
  ],
  "Soccer teams": [
    {"id": 1, "query": "List all teams", "complexity": 0, "length": 0, "tables": 1, "attributes": 3},
    {"id": 2, "query": "Show team names and leagues", "complexity": 0, "length": 1, "tables": 1, "attributes": 2},
    {"id": 3, "query": "Find teams in Serie A", "complexity": 0, "length": 1, "tables": 1, "attributes": 3},
    {"id": 4, "query": "What is the average team value by league?", "complexity": 1, "length": 1, "tables": 2, "attributes": 3},
    {"id": 5, "query": "List all players", "complexity": 0, "length": 0, "tables": 1, "attributes": 3},
    {"id": 6, "query": "Find the top 5 highest valued players", "complexity": 1, "length": 1, "tables": 1, "attributes": 4},
    {"id": 7, "query": "Show teams with their stadium capacity", "complexity": 1, "length": 1, "tables": 2, "attributes": 4},
    {"id": 8, "query": "Count players by position", "complexity": 1, "length": 1, "tables": 1, "attributes": 2},
    {"id": 9, "query": "List teams that won their league championship", "complexity": 1, "length": 1, "tables": 2, "attributes": 4},
    {"id": 10, "query": "Find players transferred in 2023", "complexity": 1, "length": 1, "tables": 2, "attributes": 5},
    {"id": 11, "query": "Show players with their current team and nationality", "complexity": 1, "length": 1, "tables": 2, "attributes": 4},
    {"id": 12, "query": "What is the total transfer spending by team in the last season?", "complexity": 2, "length": 2, "tables": 3, "attributes": 5},
    {"id": 13, "query": "Find teams that have players from more than 10 different countries", "complexity": 2, "length": 2, "tables": 3, "attributes": 6},
    {"id": 14, "query": "List top goalscorers with their team and league information", "complexity": 2, "length": 1, "tables": 3, "attributes": 7},
    {"id": 15, "query": "Show teams with the highest wage budget compared to their league average", "complexity": 3, "length": 2, "tables": 3, "attributes": 6},
    {"id": 16, "query": "Find players who played for rival teams in their career", "complexity": 3, "length": 2, "tables": 4, "attributes": 8},
    {"id": 17, "query": "Calculate each team's net transfer balance over the past 5 years", "complexity": 3, "length": 2, "tables": 3, "attributes": 7},
    {"id": 18, "query": "Show teams' performance in domestic league versus European competitions", "complexity": 3, "length": 2, "tables": 4, "attributes": 9},
    {"id": 19, "query": "Identify the most profitable player transfers based on buy and sell prices adjusted for inflation and contract details", "complexity": 3, "length": 3, "tables": 5, "attributes": 11},
    {"id": 20, "query": "Analyze youth academy effectiveness by comparing homegrown players' market value growth versus purchased players across top leagues", "complexity": 3, "length": 3, "tables": 6, "attributes": 12},
    {"id": 21, "query": "Which team has the oldest average squad age?", "complexity": 1, "length": 1, "tables": 2, "attributes": 4},
    {"id": 22, "query": "Show all goalkeepers", "complexity": 0, "length": 0, "tables": 1, "attributes": 2},
    {"id": 23, "query": "Find teams founded before 1900", "complexity": 0, "length": 1, "tables": 1, "attributes": 3},
    {"id": 24, "query": "What is the average attendance per match by team?", "complexity": 1, "length": 1, "tables": 2, "attributes": 3},
    {"id": 25, "query": "List players on loan", "complexity": 1, "length": 1, "tables": 2, "attributes": 5},
    {"id": 26, "query": "Show teams with their total trophy count", "complexity": 2, "length": 1, "tables": 3, "attributes": 4},
    {"id": 27, "query": "Find the most expensive transfer in each league", "complexity": 2, "length": 2, "tables": 3, "attributes": 6},
    {"id": 28, "query": "Which managers have won titles with multiple teams and what were their win rates?", "complexity": 3, "length": 2, "tables": 4, "attributes": 9},
    {"id": 29, "query": "Calculate the financial fair play compliance score for each team based on revenue and expenditure", "complexity": 3, "length": 3, "tables": 5, "attributes": 10},
    {"id": 30, "query": "Predict future player market values based on age, performance statistics, contract length, and transfer history patterns", "complexity": 3, "length": 3, "tables": 6, "attributes": 12}
  ],
  "Altro database": [
    {"id": 1, "query": "List all records", "complexity": 0, "length": 0, "tables": 1, "attributes": 3},
    {"id": 2, "query": "Show names and categories", "complexity": 0, "length": 1, "tables": 1, "attributes": 2},
    {"id": 3, "query": "Find items created in 2023", "complexity": 0, "length": 1, "tables": 1, "attributes": 3},
    {"id": 4, "query": "Count items by category", "complexity": 1, "length": 1, "tables": 1, "attributes": 2},
    {"id": 5, "query": "Show all active items", "complexity": 0, "length": 1, "tables": 1, "attributes": 3},
    {"id": 6, "query": "Find top 10 most viewed items", "complexity": 1, "length": 1, "tables": 1, "attributes": 4},
    {"id": 7, "query": "List items with their parent category", "complexity": 1, "length": 1, "tables": 2, "attributes": 4},
    {"id": 8, "query": "Count users by registration year", "complexity": 1, "length": 1, "tables": 1, "attributes": 2},
    {"id": 9, "query": "Show categories with more than 50 items", "complexity": 2, "length": 1, "tables": 2, "attributes": 3},
    {"id": 10, "query": "Find users who created more than 10 items", "complexity": 2, "length": 1, "tables": 2, "attributes": 4},
    {"id": 11, "query": "List items with their creator information", "complexity": 1, "length": 1, "tables": 2, "attributes": 5},
    {"id": 12, "query": "What is the average rating by category?", "complexity": 2, "length": 1, "tables": 2, "attributes": 4},
    {"id": 13, "query": "Find items with reviews from verified users only", "complexity": 2, "length": 2, "tables": 3, "attributes": 6},
    {"id": 14, "query": "Show trending items based on recent activity and views", "complexity": 2, "length": 2, "tables": 3, "attributes": 7},
    {"id": 15, "query": "List categories where average rating is above overall platform average", "complexity": 3, "length": 2, "tables": 2, "attributes": 5},
    {"id": 16, "query": "Find items that are frequently bought together", "complexity": 3, "length": 1, "tables": 3, "attributes": 7},
    {"id": 17, "query": "Calculate user engagement score based on multiple interaction types", "complexity": 3, "length": 2, "tables": 4, "attributes": 8},
    {"id": 18, "query": "Show seasonal trends in item creation and popularity across different categories", "complexity": 3, "length": 2, "tables": 4, "attributes": 9},
    {"id": 19, "query": "Identify potential fake reviews by analyzing review patterns, timing, and user behavior anomalies", "complexity": 3, "length": 3, "tables": 5, "attributes": 11},
    {"id": 20, "query": "Generate personalized recommendations based on user history, similar user preferences, and trending items in related categories", "complexity": 3, "length": 3, "tables": 6, "attributes": 12},
    {"id": 21, "query": "Which item has the highest rating?", "complexity": 1, "length": 1, "tables": 1, "attributes": 3},
    {"id": 22, "query": "Show all premium users", "complexity": 0, "length": 0, "tables": 1, "attributes": 2},
    {"id": 23, "query": "Find items updated this week", "complexity": 1, "length": 1, "tables": 1, "attributes": 3},
    {"id": 24, "query": "What is the total number of reviews?", "complexity": 1, "length": 1, "tables": 1, "attributes": 1},
    {"id": 25, "query": "List items with price discounts", "complexity": 1, "length": 1, "tables": 2, "attributes": 4},
    {"id": 26, "query": "Show user activity by month", "complexity": 2, "length": 1, "tables": 2, "attributes": 4},
    {"id": 27, "query": "Find most active contributors in each category", "complexity": 2, "length": 2, "tables": 3, "attributes": 6},
    {"id": 28, "query": "Which items have been favorited by users but never purchased?", "complexity": 3, "length": 2, "tables": 4, "attributes": 8},
    {"id": 29, "query": "Analyze churn rate by comparing active users versus inactive users over time periods", "complexity": 3, "length": 3, "tables": 4, "attributes": 9},
    {"id": 30, "query": "Predict next month's top categories based on historical trends, user demographics, and external factors", "complexity": 3, "length": 3, "tables": 6, "attributes": 12}
  ]
}
